sendi/__init__.py
sendi/__main__.py
sendi/bot.py
sendi/cli.py
sendi/common.py
sendi/lib.py
sendi/omemo.py
sendi-1.0.dist-info/METADATA
sendi-1.0.dist-info/WHEEL
sendi-1.0.dist-info/entry_points.txt
sendi-1.0.dist-info/licenses/LICENSE
sendi-1.0.dist-info/RECORD
