Metadata-Version: 2.3
Name: sendi
Version: 1.0
Summary: Another xmppsend script
Project-URL: Repository, https://framagit.org/inkhey_projects/misc/sendi
Author-email: Inkey <inkey@inkey-art.net>
License-Expression: AGPL-3.0-or-later
License-File: LICENSE
Classifier: License :: OSI Approved :: GNU Affero General Public License v3 or later (AGPLv3+)
Classifier: Programming Language :: Python :: 3
Classifier: Programming Language :: Python :: 3.11
Requires-Python: >=3.11
Requires-Dist: aiodns>=3.0.0
Requires-Dist: aiohttp>=3.8.4
Requires-Dist: annotated-types>=0.5.0
Requires-Dist: certifi>=2022.9.24
Requires-Dist: omemo>=1.1.0
Requires-Dist: pydantic<3,>=1.10.4
Requires-Dist: slixmpp-omemo>=1.1.1
Requires-Dist: slixmpp>=1.8.3
Requires-Dist: typer>=0.7.0
